{
  "namespace": "StDatepicker",
  "fsNamespace": "st-datepicker",
  "loader": "../st-datepicker.js",
  "global": "st-datepicker.global.js",
  "core": "st-datepicker.core.js",
  "corePolyfilled": "es5-build-disabled.js",
  "components": {
    "date-item-list": {
      "$": "date-item-list"
    },
    "datepicker-modal": {
      "$": "datepicker-modal"
    },
    "datepicker-range-input": {
      "$": "datepicker-modal"
    },
    "datepicker-range-modal": {
      "$": "datepicker-modal"
    },
    "datepicker-single-input": {
      "$": "datepicker-modal"
    },
    "oui-datepicker": {
      "$": "datepicker-modal"
    }
  }
}